{
  "project_info": {
    "project_number": "1025269170157",
    "project_id": "podo-49335",
    "storage_bucket": "podo-49335.appspot.com"
  },
  "client": [
    {
      "client_info": {
        "mobilesdk_app_id": "1:1025269170157:android:81e89893bd00fbd3fcf1e4",
        "android_client_info": {
          "package_name": "net.awesomekorean.newpodo"
        }
      },
      "oauth_client": [
        {
          "client_id": "1025269170157-d0tq6uta9rp3jrtcns8hth1bps6rnvrn.apps.googleusercontent.com",
          "client_type": 1,
          "android_info": {
            "package_name": "net.awesomekorean.newpodo",
            "certificate_hash": "ea34e43aeece64ac84ae4f6765a5e5756f3d18b7"
          }
        },
        {
          "client_id": "1025269170157-gs1mu6cifu03d73sa1dg58s05335rp88.apps.googleusercontent.com",
          "client_type": 3
        }
      ],
      "api_key": [
        {
          "current_key": "AIzaSyA8UMNwruFZ9e07l_-cEAHhYz_71O9D2bM"
        }
      ],
      "services": {
        "appinvite_service": {
          "other_platform_oauth_client": [
            {
              "client_id": "1025269170157-gs1mu6cifu03d73sa1dg58s05335rp88.apps.googleusercontent.com",
              "client_type": 3
            },
            {
              "client_id": "1025269170157-bo8encbak25jgt9cpkdkh9rtm71nv1q8.apps.googleusercontent.com",
              "client_type": 2,
              "ios_info": {
                "bundle_id": "net.awesomekorean.podo"
              }
            }
          ]
        }
      }
    }
  ],
  "configuration_version": "1"
}